wordCloud/__init__.py
wordCloud/example.py
wordCloud/utils.py
wordCloud/frontend/build/asset-manifest.json
wordCloud/frontend/build/bootstrap.min.css
wordCloud/frontend/build/bootstrap.min.css.map
wordCloud/frontend/build/index.html
wordCloud/frontend/build/static/css/main.6a6d8588.css
wordCloud/frontend/build/static/css/main.6a6d8588.css.map
wordCloud/frontend/build/static/js/main.0280912e.js
wordCloud/frontend/build/static/js/main.0280912e.js.LICENSE.txt
wordCloud/frontend/build/static/js/main.0280912e.js.map
wordcloud_chart-0.0.2.dist-info/LICENSE
wordcloud_chart-0.0.2.dist-info/METADATA
wordcloud_chart-0.0.2.dist-info/WHEEL
wordcloud_chart-0.0.2.dist-info/top_level.txt
wordcloud_chart-0.0.2.dist-info/RECORD
